json_file/__init__.py
json_file/json_file.py
json_file-0.1.6.dist-info/WHEEL
json_file-0.1.6.dist-info/METADATA
json_file-0.1.6.dist-info/RECORD
