Metadata-Version: 2.1
Name: json-file
Version: 0.1.6
Summary: 
Author: Eyal Levin
Author-email: eyalev@gmail.com
Requires-Python: >=3.6,<4.0
Classifier: Programming Language :: Python :: 3
Classifier: Programming Language :: Python :: 3.6
Classifier: Programming Language :: Python :: 3.7
Classifier: Programming Language :: Python :: 3.8
Requires-Dist: file-util (>=0.1.5,<0.2.0)
